Workbook

Sheet Özellik envanteri
A1: ID | B1: Özellik | C1: Kategori | D1: Uygulama durumu | E1: Uygulama kanıtı | F1: Site durumu | G1: Site kanıtı | H1: Pazarlama durumu | I1: Pazarlama kanıtı | J1: Çakışma tipi | K1: Uygulanan kural | L1: Karar | M1: Aksiyon | N1: Öncelik
A2: 01 | B2: Haftalık plan üretimi (pazar günü) | C2: PLAN VE KAYIT | D2: KISMEN VAR | E2: weekly_meal_plan_service.dart:67 — üretim istemcide, talep üzerine. Sunucuda plan üreten cron yok; functions/index.js:997 weeklyPlanReadyNotifier yalnızca pazartesi 07:00 UTC push atıyor, .limit(500) | F2: İDDİA EDİYOR | G2: hero-data.ts:731 + ozellikler/beslenme-ve-planlama.astro:15 — "Hafta, pazar günü yazıldı." | H2: GEÇİYOR | I2: basin-kiti.astro:46; HERO-CURRENT-STATE.md:117 — "haftalık yemek planı" | J2: TİP D | K2: K1 | L2: "Pazar günü" hiçbir kaynakta karşılığı olmayan bir gün. Planı kullanıcı üretir; hatırlatma pazartesi 07:00 UTC. | M2: Site: "Haftalık planını istediğin an üretirsin." 500 kullanıcı tavanı nedeniyle bildirim "herkese gider" diye anlatılmaz. | N2: YÜKSEK
A3: 02 | B3: Vücut verisine göre kişiselleştirme | C3: PLAN VE KAYIT | D3: TAM VAR | E3: calorie_calculator.dart:3-40 — Mifflin-St Jeor BMR + 5 aktivite çarpanı | F3: İDDİA EDİYOR | G3: ozellikler/beslenme-ve-planlama.astro:19 — "vücuduna, hedeflerine ve gerçekten pişirebileceğin şeylere göre" | H3: GEÇİYOR | I3: basin-kiti.astro:64 — "kullanıcının vücut verilerine ... göre üretilir" | J3: TEMİZ | K3: K3 | L3: Üç kaynak uyumlu. Site formül adını vererek somutlaşabilir. | M3: Opsiyonel: "Mifflin-St Jeor formülü" eklenir. UYARI: veri eksikse sistem sessizce 170cm/70kg/30/erkek varsayıyor (weekly_meal_plan_service.dart:301-304) → TODO. | N3: ORTA
A4: 03 | B4: Hedefe göre kişiselleştirme | C4: PLAN VE KAYIT | D4: TAM VAR | E4: calorie_calculator.dart:48-55 — adjustTDEEForGoal, sabit ±500 kcal | F4: İDDİA EDİYOR | G4: ai-yemek-plani-olusturma.astro:12 — "hedefin (kilo verme, koruma, kas kazanımı)" | H4: GEÇİYOR | I4: basin-kiti.astro:46,64 | J4: TEMİZ | K4: — | L4: Uyumlu. Kod içi tutarsızlık var: onboarding'in klinik 0,4-0,75 kg/hafta kırpması plan üretiminde kullanılmıyor. | M4: Kod içi tutarsızlık TODO'ya. Metin değişikliği gerekmiyor. | N4: ORTA
A5: 04 | B5: Alerjen filtresi | C5: PLAN VE KAYIT | D5: TAM VAR | E5: allergen_safety.dart:3-16,21 — 12 anahtar / 8 alerjen grubu; weekly_meal_plan_service.dart:90-104 havuzu önceden temizliyor, boşsa üretmeyi reddediyor | F5: İDDİA EDİYOR | G5: ozellikler/beslenme-ve-planlama.astro:24 — "filtre sen öğünleri görmeden önce uygulanır" | H5: GEÇİYOR | I5: blog/tr/alerjen-filtreleme-...md:41 — "kullanıcı öğünleri görmeden önce elenir" | J5: TEMİZ | K5: K3 | L5: Kod iddiadan GÜÇLÜ. Havuz boşsa plan üretilmiyor — site bunu söylemiyor. | M5: Sitede eklenir: "8 alerjen grubu" + "havuzda güvenli yemek kalmazsa plan üretilmez". "12 alerjen" YAZILMAZ (anahtarlar örtüşüyor). | N5: ORTA
A6: 05 | B6: Bütçeye göre plan üretimi | C6: PLAN VE KAYIT | D6: YOK | E6: budget|bütçe|cost|price → lib/, dish_data.dart, tr.json, en.json genelinde 0 sonuç. Yemek verisinde fiyat alanı yok | F6: İDDİA EDİYOR | G6: ai-yemek-plani-olusturma.astro:16 — "mutfakta ayırabileceğin süre ve haftalık bütçen" | H6: GEÇİYOR (TEK KAYNAK) | I6: basin-kiti.astro:64 — "alerjenlerine ve bütçesine göre üretilir". Sayfa :38 "düzenlenmeden kullanılması tercih edilir" diyor | J6: TİP A | K6: K7 | L6: İddia kaldırılır, özellik DEĞERLENDİR kovasına. Fiyat verisi kaynağı olmadan yapılamaz. | M6: "Bütçe" siteden ve basın kiti boilerplate'inin 4 sürümünden çıkarılır. "Süre" iddiası DOĞRULANAMADI → o da çıkar. | N6: ACİL
A7: 06 | B7: Gerçekçi ve yerel yemek seçimi | C7: PLAN VE KAYIT | D7: TAM VAR | E7: dish_data.dart — 75 yemek (kahvaltı 18 / öğle 25 / akşam 29 / ara öğün 3), TR+EN çift adlı, makro ve malzeme tam | F7: KISMEN ANILIYOR | G7: yemek-plani-uygulamasi.astro:79 — yalnızca mock örnek: "Menemen ve yulaf", "Tavuklu bulgur kâsesi". Sayı verilmiyor | H7: KISMİ | I7: HERO-CURRENT-STATE.md:93,110 — yalnızca mock | J7: TİP B | K7: K3 | L7: Sitenin kullanmadığı, DOĞRULANABİLİR tek somut rakam bu. | M7: Sitede kullanılır: "Havuzda 75 Türk yemeği var." Ara öğün yalnızca 3 → "atıştırmalık çeşitliliği" iddiası verilmez. | N7: ORTA
A8: 07 | B8: Alternatif öneriler / malzeme ikamesi | C8: PLAN VE KAYIT | D8: YOK | E8: Malzeme eşdeğerlik ikamesi hiç yok. Var olan: bütün-yemek swapMeal (weekly_meal_plan_service.dart:222) + 2 makro alternatifi (:363). swapMeal toplamları güncellemiyor (:259-277) → sessiz veri bozulması | F8: İDDİA EDİYOR | G8: ozellikler/sponsorlu-urunler.astro:43 — "sen o boşluğun alternatiflerini açtığında görünür" | H8: KISMİ | I8: DESIGN-INVENTORY.md:91 — yalnızca mock buton "Değiştir" | J8: TİP A | K8: K7 | L8: İkame iddiası kaldırılır. Ayrıca swapMeal veri doğruluğu hatası düzeltilir (S7). | M8: İddia kalkar (zaten geri çekilecek sayfada). swapMeal total_calories/macros yeniden hesabı TODO → S7. | N8: ACİL
A9: 08 | B9: Market listesi, reyona göre gruplu | C9: PLAN VE KAYIT | D9: SADECE ARAYÜZ VAR | E9: Reyon sayısı 0. Yalnızca 2 grup: shopping.to_buy / shopping.in_cart (shopping_list_screen.dart:298-301). ingredient_model.dart:1-22 — kategori/reyon alanı YOK | F9: İDDİA EDİYOR | G9: ozellikler/beslenme-ve-planlama.astro:59 — "28 öğün ... 34 ürüne indirgenir ve 7 market reyonuna göre gruplanır" (8 sayfada aynı üçlü) | H9: GEÇİYOR | I9: DESIGN-INVENTORY.md:94,109 — "28 öğünü 34 ürüne indi, 7 reyona ayrıldı" | J9: TİP A | K9: K7 + K1 | L9: 28 savunulabilir (7 gün × 4 öğün). 34 ve 7 kaynaksız, reyon özelliği yok. | M9: "34 ürün" ve "7 reyon" kaldırılır. Reyon gruplaması S8'e (Efor S) — sitenin en ucuz TİP A kapanışı. | N9: ACİL
A10: 09 | B10: Tek adımda özelleştirme — metinle | C10: PLAN VE KAYIT | D10: KISMEN VAR | E10: Serbest metinle besin analizi ve tarif üretimi VAR. Planı serbest metinle özelleştirme YOK: prompt_service.dart'ta 3 prompt, hiçbiri kullanıcı metni parametresi almıyor | F10: İDDİA EDİYOR | G10: ozellikler/yapay-zeka-koc.astro:38 — "muza çikolata sosu döktüm" | H10: GEÇİYOR (TEK KAYNAK) | I10: basin-kiti.astro:66 — "tek tek atıştırmalıklar da serbest metinle düzenlenebilir" | J10: TİP A | K10: K7 + K2 | L10: Plan düzenleme iddiası kalkar; var olan gerçek öne çıkar. | M10: Site: "...yazarsın; yapay zekâ besin değerini çıkarır ve kaydına ekler." Basın kiti cümlesi çıkar. | N10: ACİL
A11: 10 | B11: Tek adımda özelleştirme — fotoğrafla | C11: PLAN VE KAYIT | D11: KISMEN VAR | E11: Fotoğrafla KAYIT tam var (analyzeFoodPhoto). Fotoğrafla plan özelleştirme YOK | F11: ANILMIYOR | G11: Fotoğraf yalnızca kayıt yolu olarak geçiyor; plan özelleştirme kanalı olarak değil | H11: ANILMIYOR | I11: — | J11: TEMİZ | K11: — | L11: Site iddia etmiyor. Çakışma yok. | M11: Aksiyon gerekmiyor. | N11: DÜŞÜK
A12: 11 | B12: Uyum motoru: gün içi aktiviteye göre plan güncellemesi | C12: PLAN VE KAYIT | D12: YOK | E12: home.dart:1179-1198 — yakılan kalori yalnızca gösteriliyor, hedefi değiştirmiyor. weekly_meal_plan_service.dart:316-321 — yeniden üretim hash'inde kilo, aktivite, tüketim YOK | F12: İDDİA EDİYOR (ÇEKİRDEK) | G12: ozellikler/yapay-zeka-koc.astro:15 "Plan bunu zaten biliyor" + hakkimizda.astro:15 H1 + glossary/tr/adaptif-beslenme-plani.md:5 + comparisons + KEYWORD-MAP.md:14 birincil kelime | H12: GEÇİYOR (ÇEKİRDEK) | I12: TONE-OF-VOICE.md:39 "Sıfırlamak yerine" markanın kilitli karşıtlığı; personas/tr/kilo-yonetimi.md:26 | J12: TİP A | K12: K7 + K1 | L12: EN KRİTİK BULGU. Tüm konumlandırma var olmayan bir özelliğe dayanıyor. Metin bugün düzeltilir, özellik SONRA (S5, Efor L). | M12: Site: "Yakılan kalori günün üstünde görünür. Planı yeniden ürettiğinde bu veriyi hesaba katar." Sözlük tanımı daraltılır, URL korunur. | N12: ACİL
... A93: EK-14 | B93: Bakım modu / zorunlu güncelleme / hesap askıya alma | C93: EK BULGU | D93: TAM VAR | E93: lib/core/utils/route_guard.dart:125 — çalışan TEK kill-switch (bakım modu); account_suspended.* 14 localization anahtarı; zorunlu güncelleme aynı guard içinde | F93: ANILMIYOR | G93: — | H93: ANILMIYOR | I93: — | J93: TEMİZ | K93: — | L93: Altyapı. N2 için referans desen: çalışan kill-switch örneği bu. | M93: Aksiyon gerekmiyor. | N93: DÜŞÜK

Sheet Özet
A1: COOKRANGE DENETİMİ — ÖZET
A2: Kaynak: 'Özellik envanteri' sekmesi. Tüm sayılar formülle hesaplanır.
A4: Çakışma tipi | B4: Adet | C4: Anlamı
A5: TİP A | B5: =COUNTIF('Özellik envanteri'!$J$2:$J$93,A5) -> 25 | C5: Site iddia ediyor, uygulama yapmıyor — yanıltıcı beyan riski
A6: TİP A-TERS | B6: =COUNTIF('Özellik envanteri'!$J$2:$J$93,A6) -> 3 | C6: Uygulama içi metin gerçeği aşıyor (site daha dürüst)
A7: TİP B | B7: =COUNTIF('Özellik envanteri'!$J$2:$J$93,A7) -> 17 | C7: Uygulama yapıyor, site anmıyor — kaybedilen değer
A8: TİP C | B8: =COUNTIF('Özellik envanteri'!$J$2:$J$93,A8) -> 4 | C8: Aynı özellik, farklı isim — marka tutarsızlığı
A9: TİP D | B9: =COUNTIF('Özellik envanteri'!$J$2:$J$93,A9) -> 8 | C9: Aynı özellik, farklı rakam — güvenilirlik riski
A10: TİP E | B10: =COUNTIF('Özellik envanteri'!$J$2:$J$93,A10) -> 7 | C10: Kapsam uyuşmazlığı — ücretsiz/Premium, izinli/izinsiz
A11: TEMİZ | B11: =COUNTIF('Özellik envanteri'!$J$2:$J$93,A11) -> 27 | C11: Üç kaynak uyumlu
A12: BİRLEŞTİ | B12: =COUNTIF('Özellik envanteri'!$J$2:$J$93,A12) -> 1 | C12: Madde 60, madde 28 ile birleştirildi
A13: TOPLAM SATIR | B13: =COUNTA('Özellik envanteri'!$J$2:$J$93) -> 92
A15: Çakışma toplamı (TEMİZ ve BİRLEŞTİ hariç) | B15: =B13-B11-B12 -> 64
A16: Öncelik | B16: Adet
A17: ACİL | B17: =COUNTIF('Özellik envanteri'!$N$2:$N$93,A17) -> 26
A18: YÜKSEK | B18: =COUNTIF('Özellik envanteri'!$N$2:$N$93,A18) -> 19
A19: ORTA | B19: =COUNTIF('Özellik envanteri'!$N$2:$N$93,A19) -> 32
A20: DÜŞÜK | B20: =COUNTIF('Özellik envanteri'!$N$2:$N$93,A20) -> 12
A22: Kategori | B22: Satır | C22: TİP A adedi
A23: PLAN VE KAYIT | B23: =COUNTIF('Özellik envanteri'!$C$2:$C$93,A23) -> 12 | C23: =COUNTIFS('Özellik envanteri'!$C$2:$C$93,A23,'Özellik envanteri'!$J$2:$J$93,"TİP A") -> 6
A24: KAYIT YOLLARI | B24: =COUNTIF('Özellik envanteri'!$C$2:$C$93,A24) -> 6 | C24: =COUNTIFS('Özellik envanteri'!$C$2:$C$93,A24,'Özellik envanteri'!$J$2:$J$93,"TİP A") -> 2
A25: SPOR SALONU | B25: =COUNTIF('Özellik envanteri'!$C$2:$C$93,A25) -> 10 | C25: =COUNTIFS('Özellik envanteri'!$C$2:$C$93,A25,'Özellik envanteri'!$J$2:$J$93,"TİP A") -> 1
A26: KOÇ | B26: =COUNTIF('Özellik envanteri'!$C$2:$C$93,A26) -> 4 | C26: =COUNTIFS('Özellik envanteri'!$C$2:$C$93,A26,'Özellik envanteri'!$J$2:$J$93,"TİP A") -> 1
A27: TOPLULUK | B27: =COUNTIF('Özellik envanteri'!$C$2:$C$93,A27) -> 6 | C27: =COUNTIFS('Özellik envanteri'!$C$2:$C$93,A27,'Özellik envanteri'!$J$2:$J$93,"TİP A") -> 1
A28: VERİ VE İLERLEME | B28: =COUNTIF('Özellik envanteri'!$C$2:$C$93,A28) -> 3 | C28: =COUNTIFS('Özellik envanteri'!$C$2:$C$93,A28,'Özellik envanteri'!$J$2:$J$93,"TİP A") -> 2
A29: İŞ MODELİ | B29: =COUNTIF('Özellik envanteri'!$C$2:$C$93,A29) -> 6 | C29: =COUNTIFS('Özellik envanteri'!$C$2:$C$93,A29,'Özellik envanteri'!$J$2:$J$93,"TİP A") -> 4
A30: MAHREMİYET | B30: =COUNTIF('Özellik envanteri'!$C$2:$C$93,A30) -> 3 | C30: =COUNTIFS('Özellik envanteri'!$C$2:$C$93,A30,'Özellik envanteri'!$J$2:$J$93,"TİP A") -> 0
A31: PLATFORM | B31: =COUNTIF('Özellik envanteri'!$C$2:$C$93,A31) -> 3 | C31: =COUNTIFS('Özellik envanteri'!$C$2:$C$93,A31,'Özellik envanteri'!$J$2:$J$93,"TİP A") -> 0
A32: ÖNERİLEN | B32: =COUNTIF('Özellik envanteri'!$C$2:$C$93,A32) -> 8 | C32: =COUNTIFS('Özellik envanteri'!$C$2:$C$93,A32,'Özellik envanteri'!$J$2:$J$93,"TİP A") -> 0
A33: ÇAPRAZ | B33: =COUNTIF('Özellik envanteri'!$C$2:$C$93,A33) -> 17 | C33: =COUNTIFS('Özellik envanteri'!$C$2:$C$93,A33,'Özellik envanteri'!$J$2:$J$93,"TİP A") -> 8
A34: EK BULGU | B34: =COUNTIF('Özellik envanteri'!$C$2:$C$93,A34) -> 14 | C34: =COUNTIFS('Özellik envanteri'!$C$2:$C$93,A34,'Özellik envanteri'!$J$2:$J$93,"TİP A") -> 0

Sheet Okuma notu
A1: COOKRANGE ÜÇ KAYNAKLI DOĞRULUK DENETİMİ
A2: 4 Ağustos 2026
A4: RENK KODU
A5: Kırmızı = TİP A ve TİP A-TERS — yanıltıcı beyan riski, en yüksek öncelik
A6: Sarı = TİP B / C / D / E — kaybedilen değer, isim, rakam, kapsam uyuşmazlığı
A7: Yeşil = TEMİZ — üç kaynak uyumlu
A8: Gri = birleştirilmiş madde
A10: FİLTRELEME
A11: Başlık satırındaki oklardan filtrele. En sık kullanım: 'Çakışma tipi' = TİP A, ya da 'Öncelik' = ACİL.
A13: DURUM ETİKETLERİ (uygulama)
A14: TAM VAR · KISMEN VAR · SADECE ARAYÜZ VAR (UI var, arka uç yok) · YOK · DOĞRULANAMADI
A15: 'ÖZELLİK BAYRAĞI KAPALI' etiketi kullanılmadı: mekanizma var ama hiçbir yerden çağrılmıyor.
... A40: 05-SITE-DUZELTME-LISTESI.md · 06-RISK-RAPORU.md · 07-VARSAYIMLAR.md
